cueesspie-0.1.1.dist-info/licenses/LICENSE
qspy/__init__.py
qspy/config.py
qspy/core.py
qspy/functionaltags.py
qspy/contexts/__init__.py
qspy/contexts/base.py
qspy/contexts/contexts.py
qspy/examples/LR_comp.py
qspy/examples/__init__.py
qspy/experimental/__init__.py
qspy/experimental/infix_macros.py
qspy/experimental/functional_monomers/__init__.py
qspy/experimental/functional_monomers/base.py
qspy/experimental/functional_monomers/macros.py
qspy/experimental/functional_monomers/protein.py
qspy/macros/__init__.py
qspy/utils/__init__.py
qspy/utils/diagrams.py
qspy/utils/logging.py
qspy/validation/__init__.py
qspy/validation/metadata.py
qspy/validation/modelchecker.py
tests/test_full_model.py
cueesspie-0.1.1.dist-info/METADATA
cueesspie-0.1.1.dist-info/WHEEL
cueesspie-0.1.1.dist-info/top_level.txt
cueesspie-0.1.1.dist-info/RECORD
