Metadata-Version: 2.4
Name: cueesspie
Version: 0.1.1
Summary: Rule-based Programmatic Quantitative Systems Pharmacology Modeling in Python.
Author-email: "Blake A. Wilson" <blakeaw1102@gmail.com>
Project-URL: Repository, https://github.com/Borealis-BioModeling/qspy
Project-URL: Issues, https://github.com/Borealis-BioModeling/qspy/issues
Keywords: qsp,qst,pkpd,pysb
Classifier: Development Status :: 3 - Alpha
Classifier: Intended Audience :: Science/Research
Classifier: Topic :: Software Development :: Libraries :: Python Modules
Classifier: Topic :: Scientific/Engineering
Classifier: Topic :: Scientific/Engineering :: Chemistry
Classifier: License :: OSI Approved :: BSD License
Classifier: Programming Language :: Python
Classifier: Programming Language :: Python :: 3
Requires-Python: >=3.11.9
License-File: LICENSE
Requires-Dist: pysb>=1.15.0
Requires-Dist: pysb-pkpd>=0.5.3
Requires-Dist: pysb-units>=0.4.0
Requires-Dist: microbench>=0.9.1
Requires-Dist: mergram>=0.3.0
Requires-Dist: toml>=0.10.2
Requires-Dist: pyvipr>=1.0.7
Requires-Dist: seaborn>=0.13.2
Provides-Extra: dev
Requires-Dist: black>=24.4.2; extra == "dev"
Requires-Dist: pytest>=8.3.4; extra == "dev"
Requires-Dist: coverage>=7.6.10; extra == "dev"
Requires-Dist: nose>=1.3.7; extra == "dev"
Requires-Dist: mkdocs>=1.6.1; extra == "dev"
Requires-Dist: mkdocs-material>=9.6.14; extra == "dev"
Requires-Dist: mkdocstrings[python]>=1.16.11; extra == "dev"
Requires-Dist: pytkdocs[numpy-style]>=0.5.0; extra == "dev"
Provides-Extra: test
Requires-Dist: pytest>=8.3.4; extra == "test"
Requires-Dist: coverage>=7.6.10; extra == "test"
Requires-Dist: nose>=1.3.7; extra == "test"
Provides-Extra: docs
Requires-Dist: mkdocs>=1.6.1; extra == "docs"
Requires-Dist: mkdocs-material>=9.6.14; extra == "docs"
Requires-Dist: mkdocstrings[python]>=1.16.11; extra == "docs"
Requires-Dist: pytkdocs[numpy-style]>=0.5.0; extra == "docs"
Dynamic: license-file
